Metadata-Version: 2.1
Name: gb-proba
Version: 0.1
Summary: Gaussian and Binomial distributions
Home-page: UNKNOWN
Author: Ben Chan
License: UNKNOWN
Platform: UNKNOWN
